MANIFEST.in
README.rst
setup.py
qlite/__init__.py
qlite.egg-info/PKG-INFO
qlite.egg-info/SOURCES.txt
qlite.egg-info/dependency_links.txt
qlite.egg-info/top_level.txt