Metadata-Version: 1.1
Name: qlite
Version: 0.0.6
Summary: QLite is a lite project of SQLite ORM at Python3, as lite ORM for lite SQL.
Home-page: https://github.com/BorisPlus/otus_webpython_005
Author: BorisPlus
Author-email: boris-plus@mail.ru
License: UNKNOWN
Platform: UNKNOWN
Classifier: Programming Language :: Python :: 3
Classifier: Topic :: Software Development :: Libraries
Classifier: Topic :: Database
